ellar_django/__init__.py
ellar_django/commands.py
ellar_django/middleware.py
ellar_django/module.py
ellar_django_module-1.0.9.dist-info/WHEEL
ellar_django_module-1.0.9.dist-info/METADATA
ellar_django_module-1.0.9.dist-info/RECORD
